[
    {
        "Attacks": [
            {
                "Attacks": 4,
                "Dmg_Crit": 5,
                "Dmg_Hit": 2,
                "Max_Range": 2,
                "Min_Range": 0,
                "Runemark": "Axe",
                "Strength": 4
            }
        ],
        "Bladeborn": "",
        "Grand_Alliance": "Order",
        "Movement": 5,
        "Name": "Anointed",
        "Points": 180,
        "Runemarks": [
            "Hero"
        ],
        "Subtitle": "",
        "Toughness": 4,
        "Warband": "Cities of Sigmar",
        "Wounds": 18
    },
    {
        "Attacks": [
            {
                "Attacks": 5,
                "Dmg_Crit": 4,
                "Dmg_Hit": 2,
                "Max_Range": 1,
                "Min_Range": 0,
                "Runemark": "Dagger",
                "Strength": 4
            }
        ],
        "Bladeborn": "",
        "Grand_Alliance": "Order",
        "Movement": 6,
        "Name": "Assassin",
        "Points": 185,
        "Runemarks": [
            "Hero"
        ],
        "Subtitle": "",
        "Toughness": 3,
        "Warband": "Cities of Sigmar",
        "Wounds": 18
    },
    {
        "Attacks": [
            {
                "Attacks": 3,
                "Dmg_Crit": 4,
                "Dmg_Hit": 1,
                "Max_Range": 2,
                "Min_Range": 0,
                "Runemark": "Club",
                "Strength": 3
            },
            {
                "Attacks": 2,
                "Dmg_Crit": 6,
                "Dmg_Hit": 3,
                "Max_Range": 7,
                "Min_Range": 3,
                "Runemark": "Blast",
                "Strength": 3
            }
        ],
        "Bladeborn": "",
        "Grand_Alliance": "Order",
        "Movement": 4,
        "Name": "Battlemage",
        "Points": 135,
        "Runemarks": [
            "Hero",
            "Mystic"
        ],
        "Subtitle": "",
        "Toughness": 3,
        "Warband": "Cities of Sigmar",
        "Wounds": 18
    },
    {
        "Attacks": [
            {
                "Attacks": 3,
                "Dmg_Crit": 3,
                "Dmg_Hit": 1,
                "Max_Range": 1,
                "Min_Range": 0,
                "Runemark": "Sword",
                "Strength": 3
            },
            {
                "Attacks": 2,
                "Dmg_Crit": 2,
                "Dmg_Hit": 1,
                "Max_Range": 8,
                "Min_Range": 0,
                "Runemark": "Ranged Weapon",
                "Strength": 3
            }
        ],
        "Bladeborn": "",
        "Grand_Alliance": "Order",
        "Movement": 5,
        "Name": "Black Ark Cosair with Sword & Handbow",
        "Points": 75,
        "Runemarks": [
            "Scout"
        ],
        "Subtitle": "with Sword & Handbow",
        "Toughness": 3,
        "Warband": "Cities of Sigmar",
        "Wounds": 8
    },
    {
        "Attacks": [
            {
                "Attacks": 4,
                "Dmg_Crit": 3,
                "Dmg_Hit": 1,
                "Max_Range": 1,
                "Min_Range": 0,
                "Runemark": "Sword",
                "Strength": 3
            }
        ],
        "Bladeborn": "",
        "Grand_Alliance": "Order",
        "Movement": 5,
        "Name": "Black Ark Cosair with Swords",
        "Points": 65,
        "Runemarks": [
            ""
        ],
        "Subtitle": "with Swords",
        "Toughness": 3,
        "Warband": "Cities of Sigmar",
        "Wounds": 8
    },
    {
        "Attacks": [
            {
                "Attacks": 4,
                "Dmg_Crit": 4,
                "Dmg_Hit": 2,
                "Max_Range": 1,
                "Min_Range": 0,
                "Runemark": "Sword",
                "Strength": 4
            }
        ],
        "Bladeborn": "",
        "Grand_Alliance": "Order",
        "Movement": 5,
        "Name": "Black Ark Fleetmaster",
        "Points": 145,
        "Runemarks": [
            "Hero"
        ],
        "Subtitle": "",
        "Toughness": 3,
        "Warband": "Cities of Sigmar",
        "Wounds": 18
    },
    {
        "Attacks": [
            {
                "Attacks": 4,
                "Dmg_Crit": 4,
                "Dmg_Hit": 2,
                "Max_Range": 1,
                "Min_Range": 0,
                "Runemark": "Sword",
                "Strength": 3
            }
        ],
        "Bladeborn": "",
        "Grand_Alliance": "Order",
        "Movement": 5,
        "Name": "Black Ark Reaver",
        "Points": 110,
        "Runemarks": [
            "Hero"
        ],
        "Subtitle": "",
        "Toughness": 3,
        "Warband": "Cities of Sigmar",
        "Wounds": 12
    },
    {
        "Attacks": [
            {
                "Attacks": 3,
                "Dmg_Crit": 4,
                "Dmg_Hit": 2,
                "Max_Range": 2,
                "Min_Range": 0,
                "Runemark": "Axe",
                "Strength": 3
            }
        ],
        "Bladeborn": "",
        "Grand_Alliance": "Order",
        "Movement": 5,
        "Name": "Black Guard",
        "Points": 90,
        "Runemarks": [
            ""
        ],
        "Subtitle": "",
        "Toughness": 4,
        "Warband": "Cities of Sigmar",
        "Wounds": 10
    },
    {
        "Attacks": [
            {
                "Attacks": 3,
                "Dmg_Crit": 3,
                "Dmg_Hit": 1,
                "Max_Range": 1,
                "Min_Range": 0,
                "Runemark": "Sword",
                "Strength": 3
            }
        ],
        "Bladeborn": "",
        "Grand_Alliance": "Order",
        "Movement": 5,
        "Name": "Bleaksword",
        "Points": 65,
        "Runemarks": [
            "Bulwark"
        ],
        "Subtitle": "",
        "Toughness": 4,
        "Warband": "Cities of Sigmar",
        "Wounds": 8
    },
    {
        "Attacks": [
            {
                "Attacks": 4,
                "Dmg_Crit": 4,
                "Dmg_Hit": 2,
                "Max_Range": 2,
                "Min_Range": 0,
                "Runemark": "Axe",
                "Strength": 3
            }
        ],
        "Bladeborn": "",
        "Grand_Alliance": "Order",
        "Movement": 5,
        "Name": "Captain of the Black Guard",
        "Points": 135,
        "Runemarks": [
            "Hero"
        ],
        "Subtitle": "of the Black Guard",
        "Toughness": 4,
        "Warband": "Cities of Sigmar",
        "Wounds": 15
    },
    {
        "Attacks": [
            {
                "Attacks": 3,
                "Dmg_Crit": 4,
                "Dmg_Hit": 2,
                "Max_Range": 1,
                "Min_Range": 0,
                "Runemark": "Axe",
                "Strength": 4
            },
            {
                "Attacks": 2,
                "Dmg_Crit": 4,
                "Dmg_Hit": 2,
                "Max_Range": 12,
                "Min_Range": 3,
                "Runemark": "Ranged Weapon",
                "Strength": 4
            }
        ],
        "Bladeborn": "",
        "Grand_Alliance": "Order",
        "Movement": 3,
        "Name": "Cogsmith",
        "Points": 140,
        "Runemarks": [
            "Hero"
        ],
        "Subtitle": "",
        "Toughness": 4,
        "Warband": "Cities of Sigmar",
        "Wounds": 20
    },
    {
        "Attacks": [
            {
                "Attacks": 4,
                "Dmg_Crit": 4,
                "Dmg_Hit": 1,
                "Max_Range": 2,
                "Min_Range": 0,
                "Runemark": "Spear",
                "Strength": 3
            },
            {
                "Attacks": 2,
                "Dmg_Crit": 3,
                "Dmg_Hit": 1,
                "Max_Range": 12,
                "Min_Range": 3,
                "Runemark": "Ranged Weapon",
                "Strength": 3
            }
        ],
        "Bladeborn": "",
        "Grand_Alliance": "Order",
        "Movement": 10,
        "Name": "Dark Rider",
        "Points": 155,
        "Runemarks": [
            "Agile",
            "Mount"
        ],
        "Subtitle": "",
        "Toughness": 4,
        "Warband": "Cities of Sigmar",
        "Wounds": 18
    },
    {
        "Attacks": [
            {
                "Attacks": 4,
                "Dmg_Crit": 4,
                "Dmg_Hit": 2,
                "Max_Range": 1,
                "Min_Range": 0,
                "Runemark": "Axe",
                "Strength": 3
            },
            {
                "Attacks": 3,
                "Dmg_Crit": 3,
                "Dmg_Hit": 1,
                "Max_Range": 12,
                "Min_Range": 3,
                "Runemark": "Ranged Weapon",
                "Strength": 3
            }
        ],
        "Bladeborn": "",
        "Grand_Alliance": "Order",
        "Movement": 10,
        "Name": "Dark Rider Herald",
        "Points": 195,
        "Runemarks": [
            "Hero",
            "Agile",
            "Mount"
        ],
        "Subtitle": "",
        "Toughness": 4,
        "Warband": "Cities of Sigmar",
        "Wounds": 22
    },
    {
        "Attacks": [
            {
                "Attacks": 2,
                "Dmg_Crit": 2,
                "Dmg_Hit": 1,
                "Max_Range": 1,
                "Min_Range": 0,
                "Runemark": "Sword",
                "Strength": 3
            },
            {
                "Attacks": 2,
                "Dmg_Crit": 3,
                "Dmg_Hit": 1,
                "Max_Range": 12,
                "Min_Range": 3,
                "Runemark": "Ranged Weapon",
                "Strength": 3
            }
        ],
        "Bladeborn": "",
        "Grand_Alliance": "Order",
        "Movement": 5,
        "Name": "Darkshard",
        "Points": 90,
        "Runemarks": [
            "Scout"
        ],
        "Subtitle": "",
        "Toughness": 3,
        "Warband": "Cities of Sigmar",
        "Wounds": 8
    },
    {
        "Attacks": [
            {
                "Attacks": 4,
                "Dmg_Crit": 5,
                "Dmg_Hit": 2,
                "Max_Range": 2,
                "Min_Range": 0,
                "Runemark": "Spear",
                "Strength": 3
            }
        ],
        "Bladeborn": "",
        "Grand_Alliance": "Order",
        "Movement": 8,
        "Name": "Demigryph Knight",
        "Points": 180,
        "Runemarks": [
            "Elite",
            "Mount"
        ],
        "Subtitle": "",
        "Toughness": 5,
        "Warband": "Cities of Sigmar",
        "Wounds": 20
    },
    {
        "Attacks": [
            {
                "Attacks": 4,
                "Dmg_Crit": 4,
                "Dmg_Hit": 2,
                "Max_Range": 1,
                "Min_Range": 0,
                "Runemark": "Sword",
                "Strength": 4
            }
        ],
        "Bladeborn": "",
        "Grand_Alliance": "Order",
        "Movement": 5,
        "Name": "Draich Master",
        "Points": 155,
        "Runemarks": [
            "Hero",
            "Ferocious"
        ],
        "Subtitle": "",
        "Toughness": 4,
        "Warband": "Cities of Sigmar",
        "Wounds": 15
    },
    {
        "Attacks": [
            {
                "Attacks": 4,
                "Dmg_Crit": 4,
                "Dmg_Hit": 2,
                "Max_Range": 2,
                "Min_Range": 0,
                "Runemark": "Spear",
                "Strength": 3
            }
        ],
        "Bladeborn": "",
        "Grand_Alliance": "Order",
        "Movement": 8,
        "Name": "Drakespawn Knight",
        "Points": 170,
        "Runemarks": [
            "Elite",
            "Mount"
        ],
        "Subtitle": "",
        "Toughness": 5,
        "Warband": "Cities of Sigmar",
        "Wounds": 20
    },
    {
        "Attacks": [
            {
                "Attacks": 5,
                "Dmg_Crit": 4,
                "Dmg_Hit": 2,
                "Max_Range": 1,
                "Min_Range": 0,
                "Runemark": "Sword",
                "Strength": 3
            }
        ],
        "Bladeborn": "",
        "Grand_Alliance": "Order",
        "Movement": 8,
        "Name": "Dread Knight",
        "Points": 215,
        "Runemarks": [
            "Hero",
            "Mount",
            "Elite"
        ],
        "Subtitle": "",
        "Toughness": 5,
        "Warband": "Cities of Sigmar",
        "Wounds": 25
    },
    {
        "Attacks": [
            {
                "Attacks": 2,
                "Dmg_Crit": 4,
                "Dmg_Hit": 1,
                "Max_Range": 2,
                "Min_Range": 0,
                "Runemark": "Spear",
                "Strength": 3
            }
        ],
        "Bladeborn": "",
        "Grand_Alliance": "Order",
        "Movement": 5,
        "Name": "Dreadspear",
        "Points": 65,
        "Runemarks": [
            "Bulwark"
        ],
        "Subtitle": "",
        "Toughness": 4,
        "Warband": "Cities of Sigmar",
        "Wounds": 8
    },
    {
        "Attacks": [
            {
                "Attacks": 3,
                "Dmg_Crit": 4,
                "Dmg_Hit": 1,
                "Max_Range": 2,
                "Min_Range": 0,
                "Runemark": "Spear",
                "Strength": 3
            }
        ],
        "Bladeborn": "",
        "Grand_Alliance": "Order",
        "Movement": 5,
        "Name": "Eternal Guard",
        "Points": 75,
        "Runemarks": [
            "Bulwark"
        ],
        "Subtitle": "",
        "Toughness": 4,
        "Warband": "Cities of Sigmar",
        "Wounds": 8
    },
    {
        "Attacks": [
            {
                "Attacks": 4,
                "Dmg_Crit": 4,
                "Dmg_Hit": 2,
                "Max_Range": 1,
                "Min_Range": 0,
                "Runemark": "Sword",
                "Strength": 3
            }
        ],
        "Bladeborn": "",
        "Grand_Alliance": "Order",
        "Movement": 5,
        "Name": "Eternal Warden",
        "Points": 120,
        "Runemarks": [
            "Hero",
            "Bulwark"
        ],
        "Subtitle": "",
        "Toughness": 4,
        "Warband": "Cities of Sigmar",
        "Wounds": 12
    },
    {
        "Attacks": [
            {
                "Attacks": 4,
                "Dmg_Crit": 4,
                "Dmg_Hit": 2,
                "Max_Range": 1,
                "Min_Range": 0,
                "Runemark": "Sword",
                "Strength": 3
            }
        ],
        "Bladeborn": "",
        "Grand_Alliance": "Order",
        "Movement": 5,
        "Name": "Executioner",
        "Points": 100,
        "Runemarks": [
            "Ferocious"
        ],
        "Subtitle": "",
        "Toughness": 4,
        "Warband": "Cities of Sigmar",
        "Wounds": 10
    },
    {
        "Attacks": [
            {
                "Attacks": 4,
                "Dmg_Crit": 3,
                "Dmg_Hit": 1,
                "Max_Range": 1,
                "Min_Range": 0,
                "Runemark": "Club",
                "Strength": 3
            }
        ],
        "Bladeborn": "",
        "Grand_Alliance": "Order",
        "Movement": 4,
        "Name": "Flagellant",
        "Points": 65,
        "Runemarks": [
            ""
        ],
        "Subtitle": "",
        "Toughness": 3,
        "Warband": "Cities of Sigmar",
        "Wounds": 10
    },
    {
        "Attacks": [
            {
                "Attacks": 2,
                "Dmg_Crit": 2,
                "Dmg_Hit": 1,
                "Max_Range": 1,
                "Min_Range": 0,
                "Runemark": "Dagger",
                "Strength": 3
            },
            {
                "Attacks": 2,
                "Dmg_Crit": 3,
                "Dmg_Hit": 1,
                "Max_Range": 20,
                "Min_Range": 6,
                "Runemark": "Ranged Weapon",
                "Strength": 3
            }
        ],
        "Bladeborn": "",
        "Grand_Alliance": "Order",
        "Movement": 4,
        "Name": "Freeguild Crossbowman",
        "Points": 115,
        "Runemarks": [
            "Scout"
        ],
        "Subtitle": "",
        "Toughness": 3,
        "Warband": "Cities of Sigmar",
        "Wounds": 10
    },
    {
        "Attacks": [
            {
                "Attacks": 4,
                "Dmg_Crit": 4,
                "Dmg_Hit": 2,
                "Max_Range": 1,
                "Min_Range": 0,
                "Runemark": "Sword",
                "Strength": 4
            }
        ],
        "Bladeborn": "",
        "Grand_Alliance": "Order",
        "Movement": 4,
        "Name": "Freeguild General",
        "Points": 150,
        "Runemarks": [
            "Hero",
            "Ferocious"
        ],
        "Subtitle": "",
        "Toughness": 4,
        "Warband": "Cities of Sigmar",
        "Wounds": 18
    },
    {
        "Attacks": [
            {
                "Attacks": 3,
                "Dmg_Crit": 4,
                "Dmg_Hit": 2,
                "Max_Range": 1,
                "Min_Range": 0,
                "Runemark": "Sword",
                "Strength": 3
            }
        ],
        "Bladeborn": "",
        "Grand_Alliance": "Order",
        "Movement": 4,
        "Name": "Freeguild Greatsword",
        "Points": 80,
        "Runemarks": [
            "Destroyer"
        ],
        "Subtitle": "",
        "Toughness": 4,
        "Warband": "Cities of Sigmar",
        "Wounds": 10
    },
    {
        "Attacks": [
            {
                "Attacks": 3,
                "Dmg_Crit": 4,
                "Dmg_Hit": 1,
                "Max_Range": 2,
                "Min_Range": 0,
                "Runemark": "Axe",
                "Strength": 4
            }
        ],
        "Bladeborn": "",
        "Grand_Alliance": "Order",
        "Movement": 4,
        "Name": "Freeguild Guard with Halberd",
        "Points": 75,
        "Runemarks": [
            ""
        ],
        "Subtitle": "with Halberd",
        "Toughness": 3,
        "Warband": "Cities of Sigmar",
        "Wounds": 10
    },
    {
        "Attacks": [
            {
                "Attacks": 3,
                "Dmg_Crit": 4,
                "Dmg_Hit": 1,
                "Max_Range": 2,
                "Min_Range": 0,
                "Runemark": "Spear",
                "Strength": 3
            }
        ],
        "Bladeborn": "",
        "Grand_Alliance": "Order",
        "Movement": 4,
        "Name": "Freeguild Guard with Spear",
        "Points": 70,
        "Runemarks": [
            ""
        ],
        "Subtitle": "with Spear",
        "Toughness": 3,
        "Warband": "Cities of Sigmar",
        "Wounds": 10
    },
    {
        "Attacks": [
            {
                "Attacks": 3,
                "Dmg_Crit": 3,
                "Dmg_Hit": 1,
                "Max_Range": 1,
                "Min_Range": 0,
                "Runemark": "Sword",
                "Strength": 3
            }
        ],
        "Bladeborn": "",
        "Grand_Alliance": "Order",
        "Movement": 4,
        "Name": "Freeguild Guard with Sword & Shield",
        "Points": 65,
        "Runemarks": [
            "Bulwwark"
        ],
        "Subtitle": "with Sword & Shield",
        "Toughness": 4,
        "Warband": "Cities of Sigmar",
        "Wounds": 10
    },
    {
        "Attacks": [
            {
                "Attacks": 2,
                "Dmg_Crit": 2,
                "Dmg_Hit": 1,
                "Max_Range": 1,
                "Min_Range": 0,
                "Runemark": "Dagger",
                "Strength": 3
            },
            {
                "Attacks": 2,
                "Dmg_Crit": 3,
                "Dmg_Hit": 1,
                "Max_Range": 12,
                "Min_Range": 3,
                "Runemark": "Ranged Weapon",
                "Strength": 4
            }
        ],
        "Bladeborn": "",
        "Grand_Alliance": "Order",
        "Movement": 4,
        "Name": "Freeguild Handgunner",
        "Points": 90,
        "Runemarks": [
            "Scout"
        ],
        "Subtitle": "",
        "Toughness": 3,
        "Warband": "Cities of Sigmar",
        "Wounds": 10
    },
    {
        "Attacks": [
            {
                "Attacks": 4,
                "Dmg_Crit": 3,
                "Dmg_Hit": 1,
                "Max_Range": 1,
                "Min_Range": 0,
                "Runemark": "Sword",
                "Strength": 3
            },
            {
                "Attacks": 3,
                "Dmg_Crit": 3,
                "Dmg_Hit": 1,
                "Max_Range": 12,
                "Min_Range": 3,
                "Runemark": "Ranged Weapon",
                "Strength": 4
            }
        ],
        "Bladeborn": "",
        "Grand_Alliance": "Order",
        "Movement": 10,
        "Name": "Freeguild Outrider",
        "Points": 160,
        "Runemarks": [
            "Agile",
            "Mount"
        ],
        "Subtitle": "",
        "Toughness": 3,
        "Warband": "Cities of Sigmar",
        "Wounds": 18
    },
    {
        "Attacks": [
            {
                "Attacks": 4,
                "Dmg_Crit": 3,
                "Dmg_Hit": 1,
                "Max_Range": 1,
                "Min_Range": 0,
                "Runemark": "Dagger",
                "Strength": 3
            },
            {
                "Attacks": 3,
                "Dmg_Crit": 3,
                "Dmg_Hit": 1,
                "Max_Range": 8,
                "Min_Range": 0,
                "Runemark": "Ranged Weapon",
                "Strength": 3
            }
        ],
        "Bladeborn": "",
        "Grand_Alliance": "Order",
        "Movement": 10,
        "Name": "Freeguild Pistoleer",
        "Points": 135,
        "Runemarks": [
            "Agile",
            "Mount"
        ],
        "Subtitle": "",
        "Toughness": 3,
        "Warband": "Cities of Sigmar",
        "Wounds": 18
    },
    {
        "Attacks": [
            {
                "Attacks": 3,
                "Dmg_Crit": 4,
                "Dmg_Hit": 2,
                "Max_Range": 1,
                "Min_Range": 0,
                "Runemark": "Sword",
                "Strength": 4
            }
        ],
        "Bladeborn": "",
        "Grand_Alliance": "Order",
        "Movement": 4,
        "Name": "Freeguild Sergeant",
        "Points": 110,
        "Runemarks": [
            "Hero"
        ],
        "Subtitle": "",
        "Toughness": 3,
        "Warband": "Cities of Sigmar",
        "Wounds": 15
    },
    {
        "Attacks": [
            {
                "Attacks": 3,
                "Dmg_Crit": 3,
                "Dmg_Hit": 1,
                "Max_Range": 1,
                "Min_Range": 0,
                "Runemark": "Dagger",
                "Strength": 3
            },
            {
                "Attacks": 3,
                "Dmg_Crit": 3,
                "Dmg_Hit": 1,
                "Max_Range": 12,
                "Min_Range": 3,
                "Runemark": "Ranged Weapon",
                "Strength": 3
            }
        ],
        "Bladeborn": "",
        "Grand_Alliance": "Order",
        "Movement": 5,
        "Name": "Guardmaster",
        "Points": 125,
        "Runemarks": [
            "Hero"
        ],
        "Subtitle": "",
        "Toughness": 3,
        "Warband": "Cities of Sigmar",
        "Wounds": 12
    },
    {
        "Attacks": [
            {
                "Attacks": 4,
                "Dmg_Crit": 4,
                "Dmg_Hit": 2,
                "Max_Range": 1,
                "Min_Range": 0,
                "Runemark": "Sword",
                "Strength": 4
            }
        ],
        "Bladeborn": "",
        "Grand_Alliance": "Order",
        "Movement": 4,
        "Name": "Guild Champion",
        "Points": 145,
        "Runemarks": [
            "Hero",
            "Ferocious"
        ],
        "Subtitle": "",
        "Toughness": 4,
        "Warband": "Cities of Sigmar",
        "Wounds": 15
    },
    {
        "Attacks": [
            {
                "Attacks": 3,
                "Dmg_Crit": 4,
                "Dmg_Hit": 2,
                "Max_Range": 1,
                "Min_Range": 0,
                "Runemark": "Blast",
                "Strength": 5
            },
            {
                "Attacks": 3,
                "Dmg_Crit": 3,
                "Dmg_Hit": 1,
                "Max_Range": 15,
                "Min_Range": 3,
                "Runemark": "Ranged Weapon",
                "Strength": 4
            }
        ],
        "Bladeborn": "",
        "Grand_Alliance": "Order",
        "Movement": 10,
        "Name": "Gyrobomber",
        "Points": 220,
        "Runemarks": [
            "Fly"
        ],
        "Subtitle": "",
        "Toughness": 4,
        "Warband": "Cities of Sigmar",
        "Wounds": 25
    },
    {
        "Attacks": [
            {
                "Attacks": 2,
                "Dmg_Crit": 4,
                "Dmg_Hit": 2,
                "Max_Range": 1,
                "Min_Range": 0,
                "Runemark": "Blast",
                "Strength": 4
            },
            {
                "Attacks": 2,
                "Dmg_Crit": 3,
                "Dmg_Hit": 1,
                "Max_Range": 12,
                "Min_Range": 3,
                "Runemark": "Ranged Weapon",
                "Strength": 4
            }
        ],
        "Bladeborn": "",
        "Grand_Alliance": "Order",
        "Movement": 12,
        "Name": "Gyrocopter",
        "Points": 195,
        "Runemarks": [
            "Fly"
        ],
        "Subtitle": "",
        "Toughness": 4,
        "Warband": "Cities of Sigmar",
        "Wounds": 22
    },
    {
        "Attacks": [
            {
                "Attacks": 3,
                "Dmg_Crit": 5,
                "Dmg_Hit": 2,
                "Max_Range": 1,
                "Min_Range": 0,
                "Runemark": "Hammer",
                "Strength": 4
            }
        ],
        "Bladeborn": "",
        "Grand_Alliance": "Order",
        "Movement": 3,
        "Name": "Hammerer",
        "Points": 80,
        "Runemarks": [
            "Destroyer"
        ],
        "Subtitle": "",
        "Toughness": 4,
        "Warband": "Cities of Sigmar",
        "Wounds": 12
    },
    {
        "Attacks": [
            {
                "Attacks": 4,
                "Dmg_Crit": 4,
                "Dmg_Hit": 2,
                "Max_Range": 2,
                "Min_Range": 0,
                "Runemark": "Club",
                "Strength": 3
            },
            {
                "Attacks": 3,
                "Dmg_Crit": 4,
                "Dmg_Hit": 2,
                "Max_Range": 8,
                "Min_Range": 0,
                "Runemark": "Spear",
                "Strength": 3
            }
        ],
        "Bladeborn": "",
        "Grand_Alliance": "Order",
        "Movement": 10,
        "Name": "Handmaiden of the Thorn",
        "Points": 190,
        "Runemarks": [
            "Hero",
            "Mystic",
            "Mount"
        ],
        "Subtitle": "of the Thorn",
        "Toughness": 3,
        "Warband": "Cities of Sigmar",
        "Wounds": 22
    },
    {
        "Attacks": [
            {
                "Attacks": 3,
                "Dmg_Crit": 4,
                "Dmg_Hit": 2,
                "Max_Range": 1,
                "Min_Range": 0,
                "Runemark": "Sword",
                "Strength": 3
            },
            {
                "Attacks": 3,
                "Dmg_Crit": 3,
                "Dmg_Hit": 1,
                "Max_Range": 15,
                "Min_Range": 3,
                "Runemark": "Ranged Weapon",
                "Strength": 4
            }
        ],
        "Bladeborn": "",
        "Grand_Alliance": "Order",
        "Movement": 5,
        "Name": "High Sister",
        "Points": 145,
        "Runemarks": [
            "Hero",
            "Scout"
        ],
        "Subtitle": "",
        "Toughness": 3,
        "Warband": "Cities of Sigmar",
        "Wounds": 12
    },
    {
        "Attacks": [
            {
                "Attacks": 2,
                "Dmg_Crit": 4,
                "Dmg_Hit": 2,
                "Max_Range": 5,
                "Min_Range": 3,
                "Runemark": "Blast",
                "Strength": 4
            },
            {
                "Attacks": 3,
                "Dmg_Crit": 3,
                "Dmg_Hit": 1,
                "Max_Range": 8,
                "Min_Range": 1,
                "Runemark": "Ranged Weapon",
                "Strength": 3
            }
        ],
        "Bladeborn": "",
        "Grand_Alliance": "Order",
        "Movement": 3,
        "Name": "Ironbeard with Drakefire Pistol and Cinderblast Bomb",
        "Points": 120,
        "Runemarks": [
            "Hero"
        ],
        "Subtitle": "with Drakefire Pistol and Cinderblast Bomb",
        "Toughness": 4,
        "Warband": "Cities of Sigmar",
        "Wounds": 16
    },
    {
        "Attacks": [
            {
                "Attacks": 3,
                "Dmg_Crit": 3,
                "Dmg_Hit": 1,
                "Max_Range": 1,
                "Min_Range": 0,
                "Runemark": "Hammer",
                "Strength": 3
            }
        ],
        "Bladeborn": "",
        "Grand_Alliance": "Order",
        "Movement": 3,
        "Name": "Ironbreaker",
        "Points": 60,
        "Runemarks": [
            "Bulwark"
        ],
        "Subtitle": "",
        "Toughness": 5,
        "Warband": "Cities of Sigmar",
        "Wounds": 12
    },
    {
        "Attacks": [
            {
                "Attacks": 2,
                "Dmg_Crit": 2,
                "Dmg_Hit": 1,
                "Max_Range": 1,
                "Min_Range": 0,
                "Runemark": "Unarmed",
                "Strength": 3
            },
            {
                "Attacks": 2,
                "Dmg_Crit": 4,
                "Dmg_Hit": 1,
                "Max_Range": 12,
                "Min_Range": 3,
                "Runemark": "Ranged Weapon",
                "Strength": 3
            }
        ],
        "Bladeborn": "",
        "Grand_Alliance": "Order",
        "Movement": 3,
        "Name": "Irondrake",
        "Points": 85,
        "Runemarks": [
            "Scout"
        ],
        "Subtitle": "",
        "Toughness": 4,
        "Warband": "Cities of Sigmar",
        "Wounds": 12
    },
    {
        "Attacks": [
            {
                "Attacks": 3,
                "Dmg_Crit": 3,
                "Dmg_Hit": 1,
                "Max_Range": 1,
                "Min_Range": 0,
                "Runemark": "Unarmed",
                "Strength": 3
            },
            {
                "Attacks": 2,
                "Dmg_Crit": 5,
                "Dmg_Hit": 2,
                "Max_Range": 15,
                "Min_Range": 3,
                "Runemark": "Ranged Weapon",
                "Strength": 5
            }
        ],
        "Bladeborn": "",
        "Grand_Alliance": "Order",
        "Movement": 3,
        "Name": "Ironwarden with Grudgehammer Torpedo",
        "Points": 155,
        "Runemarks": [
            "Hero"
        ],
        "Subtitle": "with Grudgehammer Torpedo",
        "Toughness": 4,
        "Warband": "Cities of Sigmar",
        "Wounds": 16
    },
    {
        "Attacks": [
            {
                "Attacks": 4,
                "Dmg_Crit": 4,
                "Dmg_Hit": 2,
                "Max_Range": 2,
                "Min_Range": 0,
                "Runemark": "Axe",
                "Strength": 4
            }
        ],
        "Bladeborn": "",
        "Grand_Alliance": "Order",
        "Movement": 5,
        "Name": "Keeper of the Flame",
        "Points": 160,
        "Runemarks": [
            "Hero"
        ],
        "Subtitle": "",
        "Toughness": 4,
        "Warband": "Cities of Sigmar",
        "Wounds": 15
    },
    {
        "Attacks": [
            {
                "Attacks": 4,
                "Dmg_Crit": 5,
                "Dmg_Hit": 2,
                "Max_Range": 1,
                "Min_Range": 0,
                "Runemark": "Hammer",
                "Strength": 4
            }
        ],
        "Bladeborn": "",
        "Grand_Alliance": "Order",
        "Movement": 3,
        "Name": "Keeper of the Gate",
        "Points": 130,
        "Runemarks": [
            "Hero",
            "Destroyer"
        ],
        "Subtitle": "",
        "Toughness": 4,
        "Warband": "Cities of Sigmar",
        "Wounds": 16
    },
    {
        "Attacks": [
            {
                "Attacks": 3,
                "Dmg_Crit": 4,
                "Dmg_Hit": 2,
                "Max_Range": 1,
                "Min_Range": 0,
                "Runemark": "Axe",
                "Strength": 4
            }
        ],
        "Bladeborn": "",
        "Grand_Alliance": "Order",
        "Movement": 3,
        "Name": "Longbeard with Greataxe",
        "Points": 75,
        "Runemarks": [
            "Destroyer"
        ],
        "Subtitle": "with Greataxe",
        "Toughness": 4,
        "Warband": "Cities of Sigmar",
        "Wounds": 12
    },
    {
        "Attacks": [
            {
                "Attacks": 3,
                "Dmg_Crit": 4,
                "Dmg_Hit": 2,
                "Max_Range": 1,
                "Min_Range": 0,
                "Runemark": "Hammer",
                "Strength": 3
            }
        ],
        "Bladeborn": "",
        "Grand_Alliance": "Order",
        "Movement": 3,
        "Name": "Longbeard with Hammer & Shield",
        "Points": 70,
        "Runemarks": [
            "Bulwark"
        ],
        "Subtitle": "with Hammer & Shield",
        "Toughness": 5,
        "Warband": "Cities of Sigmar",
        "Wounds": 12
    },
    {
        "Attacks": [
            {
                "Attacks": 3,
                "Dmg_Crit": 4,
                "Dmg_Hit": 2,
                "Max_Range": 1,
                "Min_Range": 0,
                "Runemark": "Sword",
                "Strength": 3
            }
        ],
        "Bladeborn": "",
        "Grand_Alliance": "Order",
        "Movement": 5,
        "Name": "Lordling",
        "Points": 105,
        "Runemarks": [
            "Hero",
            "Bulwark"
        ],
        "Subtitle": "",
        "Toughness": 4,
        "Warband": "Cities of Sigmar",
        "Wounds": 12
    },
    {
        "Attacks": [
            {
                "Attacks": 3,
                "Dmg_Crit": 3,
                "Dmg_Hit": 1,
                "Max_Range": 1,
                "Min_Range": 0,
                "Runemark": "Dagger",
                "Strength": 3
            },
            {
                "Attacks": 3,
                "Dmg_Crit": 3,
                "Dmg_Hit": 1,
                "Max_Range": 12,
                "Min_Range": 3,
                "Runemark": "Ranged Weapon",
                "Strength": 4
            }
        ],
        "Bladeborn": "",
        "Grand_Alliance": "Order",
        "Movement": 4,
        "Name": "Marksman with Repeater Handgun",
        "Points": 140,
        "Runemarks": [
            "Hero",
            "Agile"
        ],
        "Subtitle": "with Repeater Handgun",
        "Toughness": 3,
        "Warband": "Cities of Sigmar",
        "Wounds": 15
    },
    {
        "Attacks": [
            {
                "Attacks": 3,
                "Dmg_Crit": 3,
                "Dmg_Hit": 1,
                "Max_Range": 1,
                "Min_Range": 0,
                "Runemark": "Dagger",
                "Strength": 3
            },
            {
                "Attacks": 1,
                "Dmg_Crit": 10,
                "Dmg_Hit": 4,
                "Max_Range": 20,
                "Min_Range": 6,
                "Runemark": "Ranged Weapon",
                "Strength": 4
            }
        ],
        "Bladeborn": "",
        "Grand_Alliance": "Order",
        "Movement": 4,
        "Name": "Marksman with Long Rifle",
        "Points": 165,
        "Runemarks": [
            "Hero"
        ],
        "Subtitle": "with Long Rifle",
        "Toughness": 3,
        "Warband": "Cities of Sigmar",
        "Wounds": 15
    },
    {
        "Attacks": [
            {
                "Attacks": 4,
                "Dmg_Crit": 4,
                "Dmg_Hit": 2,
                "Max_Range": 2,
                "Min_Range": 0,
                "Runemark": "Spear",
                "Strength": 4
            },
            {
                "Attacks": 2,
                "Dmg_Crit": 2,
                "Dmg_Hit": 1,
                "Max_Range": 20,
                "Min_Range": 6,
                "Runemark": "Claws",
                "Strength": 3
            }
        ],
        "Bladeborn": "",
        "Grand_Alliance": "Order",
        "Movement": 5,
        "Name": "Nomad Prince",
        "Points": 170,
        "Runemarks": [
            "Hero",
            "Bulwark"
        ],
        "Subtitle": "",
        "Toughness": 4,
        "Warband": "Cities of Sigmar",
        "Wounds": 18
    },
    {
        "Attacks": [
            {
                "Attacks": 4,
                "Dmg_Crit": 4,
                "Dmg_Hit": 2,
                "Max_Range": 1,
                "Min_Range": 0,
                "Runemark": "Axe",
                "Strength": 3
            }
        ],
        "Bladeborn": "",
        "Grand_Alliance": "Order",
        "Movement": 3,
        "Name": "Old Guard with Weapon and Shield",
        "Points": 110,
        "Runemarks": [
            "Hero",
            "Bulwark"
        ],
        "Subtitle": "with Weapon and Shield",
        "Toughness": 5,
        "Warband": "Cities of Sigmar",
        "Wounds": 16
    },
    {
        "Attacks": [
            {
                "Attacks": 3,
                "Dmg_Crit": 4,
                "Dmg_Hit": 2,
                "Max_Range": 2,
                "Min_Range": 0,
                "Runemark": "Axe",
                "Strength": 4
            }
        ],
        "Bladeborn": "",
        "Grand_Alliance": "Order",
        "Movement": 5,
        "Name": "Phoenix Guard",
        "Points": 105,
        "Runemarks": [
            ""
        ],
        "Subtitle": "",
        "Toughness": 4,
        "Warband": "Cities of Sigmar",
        "Wounds": 10
    },
    {
        "Attacks": [
            {
                "Attacks": 4,
                "Dmg_Crit": 4,
                "Dmg_Hit": 2,
                "Max_Range": 1,
                "Min_Range": 0,
                "Runemark": "Sword",
                "Strength": 4
            }
        ],
        "Bladeborn": "",
        "Grand_Alliance": "Order",
        "Movement": 8,
        "Name": "Preceptor",
        "Points": 225,
        "Runemarks": [
            "Hero",
            "Elite",
            "Mount"
        ],
        "Subtitle": "",
        "Toughness": 5,
        "Warband": "Cities of Sigmar",
        "Wounds": 25
    },
    {
        "Attacks": [
            {
                "Attacks": 4,
                "Dmg_Crit": 4,
                "Dmg_Hit": 2,
                "Max_Range": 1,
                "Min_Range": 0,
                "Runemark": "Club",
                "Strength": 3
            }
        ],
        "Bladeborn": "",
        "Grand_Alliance": "Order",
        "Movement": 4,
        "Name": "Prophet",
        "Points": 110,
        "Runemarks": [
            "Hero"
        ],
        "Subtitle": "",
        "Toughness": 3,
        "Warband": "Cities of Sigmar",
        "Wounds": 15
    },
    {
        "Attacks": [
            {
                "Attacks": 3,
                "Dmg_Crit": 4,
                "Dmg_Hit": 2,
                "Max_Range": 1,
                "Min_Range": 0,
                "Runemark": "Hammer",
                "Strength": 4
            }
        ],
        "Bladeborn": "",
        "Grand_Alliance": "Order",
        "Movement": 3,
        "Name": "Runelord",
        "Points": 120,
        "Runemarks": [
            "Hero",
            "Priest"
        ],
        "Subtitle": "",
        "Toughness": 4,
        "Warband": "Cities of Sigmar",
        "Wounds": 20
    },
    {
        "Attacks": [
            {
                "Attacks": 3,
                "Dmg_Crit": 4,
                "Dmg_Hit": 2,
                "Max_Range": 1,
                "Min_Range": 0,
                "Runemark": "Sword",
                "Strength": 3
            },
            {
                "Attacks": 3,
                "Dmg_Crit": 3,
                "Dmg_Hit": 1,
                "Max_Range": 15,
                "Min_Range": 3,
                "Runemark": "Ranged Weapon",
                "Strength": 3
            }
        ],
        "Bladeborn": "",
        "Grand_Alliance": "Order",
        "Movement": 5,
        "Name": "Shadow Walker",
        "Points": 135,
        "Runemarks": [
            "Hero",
            "Scout"
        ],
        "Subtitle": "",
        "Toughness": 3,
        "Warband": "Cities of Sigmar",
        "Wounds": 12
    },
    {
        "Attacks": [
            {
                "Attacks": 3,
                "Dmg_Crit": 3,
                "Dmg_Hit": 1,
                "Max_Range": 1,
                "Min_Range": 0,
                "Runemark": "Sword",
                "Strength": 3
            },
            {
                "Attacks": 2,
                "Dmg_Crit": 3,
                "Dmg_Hit": 1,
                "Max_Range": 15,
                "Min_Range": 3,
                "Runemark": "Ranged Weapon",
                "Strength": 3
            }
        ],
        "Bladeborn": "",
        "Grand_Alliance": "Order",
        "Movement": 5,
        "Name": "Shadow Warrior",
        "Points": 100,
        "Runemarks": [
            "Scout"
        ],
        "Subtitle": "",
        "Toughness": 3,
        "Warband": "Cities of Sigmar",
        "Wounds": 8
    },
    {
        "Attacks": [
            {
                "Attacks": 4,
                "Dmg_Crit": 4,
                "Dmg_Hit": 2,
                "Max_Range": 1,
                "Min_Range": 0,
                "Runemark": "Sword",
                "Strength": 3
            },
            {
                "Attacks": 2,
                "Dmg_Crit": 5,
                "Dmg_Hit": 2,
                "Max_Range": 10,
                "Min_Range": 3,
                "Runemark": "Ranged Weapon",
                "Strength": 6
            }
        ],
        "Bladeborn": "",
        "Grand_Alliance": "Order",
        "Movement": 10,
        "Name": "Sharpshooter Grenade-Launching Blunderbuss",
        "Points": 205,
        "Runemarks": [
            "Agile",
            "Hero",
            "Mount"
        ],
        "Subtitle": "Grenade-Launching Blunderbuss",
        "Toughness": 3,
        "Warband": "Cities of Sigmar",
        "Wounds": 22
    },
    {
        "Attacks": [
            {
                "Attacks": 4,
                "Dmg_Crit": 3,
                "Dmg_Hit": 1,
                "Max_Range": 2,
                "Min_Range": 0,
                "Runemark": "Club",
                "Strength": 3
            },
            {
                "Attacks": 2,
                "Dmg_Crit": 4,
                "Dmg_Hit": 1,
                "Max_Range": 8,
                "Min_Range": 0,
                "Runemark": "Spear",
                "Strength": 3
            }
        ],
        "Bladeborn": "",
        "Grand_Alliance": "Order",
        "Movement": 10,
        "Name": "Sister of the Thorn",
        "Points": 130,
        "Runemarks": [
            "Mount"
        ],
        "Subtitle": "",
        "Toughness": 3,
        "Warband": "Cities of Sigmar",
        "Wounds": 18
    },
    {
        "Attacks": [
            {
                "Attacks": 3,
                "Dmg_Crit": 3,
                "Dmg_Hit": 1,
                "Max_Range": 1,
                "Min_Range": 0,
                "Runemark": "Sword",
                "Strength": 3
            },
            {
                "Attacks": 2,
                "Dmg_Crit": 3,
                "Dmg_Hit": 1,
                "Max_Range": 15,
                "Min_Range": 3,
                "Runemark": "Ranged Weapon",
                "Strength": 4
            }
        ],
        "Bladeborn": "",
        "Grand_Alliance": "Order",
        "Movement": 5,
        "Name": "Sister of the Watch",
        "Points": 100,
        "Runemarks": [
            "Scout"
        ],
        "Subtitle": "",
        "Toughness": 3,
        "Warband": "Cities of Sigmar",
        "Wounds": 8
    },
    {
        "Attacks": [
            {
                "Attacks": 3,
                "Dmg_Crit": 4,
                "Dmg_Hit": 1,
                "Max_Range": 2,
                "Min_Range": 0,
                "Runemark": "Club",
                "Strength": 3
            },
            {
                "Attacks": 2,
                "Dmg_Crit": 6,
                "Dmg_Hit": 3,
                "Max_Range": 7,
                "Min_Range": 3,
                "Runemark": "Blast",
                "Strength": 3
            }
        ],
        "Bladeborn": "",
        "Grand_Alliance": "Order",
        "Movement": 5,
        "Name": "Sorceress",
        "Points": 140,
        "Runemarks": [
            "Hero",
            "Mystic"
        ],
        "Subtitle": "",
        "Toughness": 3,
        "Warband": "Cities of Sigmar",
        "Wounds": 18
    },
    {
        "Attacks": [
            {
                "Attacks": 4,
                "Dmg_Crit": 5,
                "Dmg_Hit": 2,
                "Max_Range": 1,
                "Min_Range": 0,
                "Runemark": "Hammer",
                "Strength": 4
            }
        ],
        "Bladeborn": "",
        "Grand_Alliance": "Order",
        "Movement": 3,
        "Name": "Warden King",
        "Points": 170,
        "Runemarks": [
            "Hero",
            "Bulwark"
        ],
        "Subtitle": "",
        "Toughness": 5,
        "Warband": "Cities of Sigmar",
        "Wounds": 22
    },
    {
        "Attacks": [
            {
                "Attacks": 5,
                "Dmg_Crit": 4,
                "Dmg_Hit": 2,
                "Max_Range": 1,
                "Min_Range": 0,
                "Runemark": "Sword",
                "Strength": 4
            }
        ],
        "Bladeborn": "",
        "Grand_Alliance": "Order",
        "Movement": 10,
        "Name": "Wild Hunter",
        "Points": 225,
        "Runemarks": [
            "Hero",
            "Elite",
            "Mount"
        ],
        "Subtitle": "",
        "Toughness": 3,
        "Warband": "Cities of Sigmar",
        "Wounds": 22
    },
    {
        "Attacks": [
            {
                "Attacks": 4,
                "Dmg_Crit": 4,
                "Dmg_Hit": 2,
                "Max_Range": 2,
                "Min_Range": 0,
                "Runemark": "Spear",
                "Strength": 4
            }
        ],
        "Bladeborn": "",
        "Grand_Alliance": "Order",
        "Movement": 10,
        "Name": "Wild Rider",
        "Points": 180,
        "Runemarks": [
            "Elite",
            "Mount"
        ],
        "Subtitle": "",
        "Toughness": 3,
        "Warband": "Cities of Sigmar",
        "Wounds": 18
    },
    {
        "Attacks": [
            {
                "Attacks": 3,
                "Dmg_Crit": 4,
                "Dmg_Hit": 2,
                "Max_Range": 2,
                "Min_Range": 0,
                "Runemark": "Axe",
                "Strength": 4
            }
        ],
        "Bladeborn": "",
        "Grand_Alliance": "Order",
        "Movement": 5,
        "Name": "Wildwood Ranger",
        "Points": 100,
        "Runemarks": [
            "Destroyer"
        ],
        "Subtitle": "",
        "Toughness": 3,
        "Warband": "Cities of Sigmar",
        "Wounds": 8
    },
    {
        "Attacks": [
            {
                "Attacks": 4,
                "Dmg_Crit": 4,
                "Dmg_Hit": 2,
                "Max_Range": 1,
                "Min_Range": 0,
                "Runemark": "Axe",
                "Strength": 4
            }
        ],
        "Bladeborn": "",
        "Grand_Alliance": "Order",
        "Movement": 5,
        "Name": "Wildwood Warden",
        "Points": 140,
        "Runemarks": [
            "Hero",
            "Destroyer"
        ],
        "Subtitle": "",
        "Toughness": 3,
        "Warband": "Cities of Sigmar",
        "Wounds": 12
    }
]