[
    {
        "_id": "a9714107",
        "name": "Skink with Moonstone Club and Star-buckler",
        "warband": "Seraphon",
        "subfaction": "",
        "grand_alliance": "order",
        "movement": 6,
        "toughness": 3,
        "wounds": 8,
        "weapons": [
            {
                "attacks": 3,
                "dmg_crit": 3,
                "dmg_hit": 1,
                "max_range": 1,
                "min_range": 0,
                "runemark": "club",
                "strength": 2
            }
        ],
        "runemarks": [
            "minion"
        ],
        "points": 65
    },
    {
        "_id": "36d26aad",
        "name": "Skink Handler",
        "warband": "Seraphon",
        "subfaction": "",
        "grand_alliance": "order",
        "movement": 6,
        "toughness": 2,
        "wounds": 8,
        "weapons": [
            {
                "attacks": 2,
                "dmg_crit": 4,
                "dmg_hit": 1,
                "max_range": 2,
                "min_range": 0,
                "runemark": "club",
                "strength": 2
            }
        ],
        "runemarks": [
            "minion",
            "trapper"
        ],
        "points": 65
    },
    {
        "_id": "92d950bd",
        "name": "Skink with Boltspitter and Moonstone Club",
        "warband": "Seraphon",
        "subfaction": "",
        "grand_alliance": "order",
        "movement": 6,
        "toughness": 2,
        "wounds": 8,
        "weapons": [
            {
                "attacks": 3,
                "dmg_crit": 3,
                "dmg_hit": 1,
                "max_range": 1,
                "min_range": 0,
                "runemark": "club",
                "strength": 2
            },
            {
                "attacks": 2,
                "dmg_crit": 2,
                "dmg_hit": 1,
                "max_range": 8,
                "min_range": 0,
                "runemark": "ranged",
                "strength": 1
            }
        ],
        "runemarks": [
            "minion"
        ],
        "points": 75
    },
    {
        "_id": "1e674f31",
        "name": "Skink with Meteoric Javelin and Star-buckler",
        "warband": "Seraphon",
        "subfaction": "",
        "grand_alliance": "order",
        "movement": 6,
        "toughness": 3,
        "wounds": 8,
        "weapons": [
            {
                "attacks": 3,
                "dmg_crit": 3,
                "dmg_hit": 1,
                "max_range": 1,
                "min_range": 0,
                "runemark": "spear",
                "strength": 2
            },
            {
                "attacks": 1,
                "dmg_crit": 4,
                "dmg_hit": 1,
                "max_range": 8,
                "min_range": 0,
                "runemark": "ranged",
                "strength": 3
            }
        ],
        "runemarks": [
            "minion"
        ],
        "points": 80
    },
    {
        "_id": "f240ce35",
        "name": "Saurus Warrior with Celestite Club",
        "warband": "Seraphon",
        "subfaction": "",
        "grand_alliance": "order",
        "movement": 4,
        "toughness": 4,
        "wounds": 12,
        "weapons": [
            {
                "attacks": 4,
                "dmg_crit": 3,
                "dmg_hit": 1,
                "max_range": 1,
                "min_range": 0,
                "runemark": "club",
                "strength": 4
            }
        ],
        "runemarks": [
            "warrior"
        ],
        "points": 85
    },
    {
        "_id": "c7032f04",
        "name": "Saurus Warrior with Celestite Spear",
        "warband": "Seraphon",
        "subfaction": "",
        "grand_alliance": "order",
        "movement": 4,
        "toughness": 4,
        "wounds": 12,
        "weapons": [
            {
                "attacks": 3,
                "dmg_crit": 4,
                "dmg_hit": 1,
                "max_range": 2,
                "min_range": 0,
                "runemark": "spear",
                "strength": 4
            }
        ],
        "runemarks": [
            "warrior"
        ],
        "points": 90
    },
    {
        "_id": "fe03cd8f",
        "name": "Skink Alpha with Moonstone Club and Star-buckler",
        "warband": "Seraphon",
        "subfaction": "",
        "grand_alliance": "order",
        "movement": 6,
        "toughness": 3,
        "wounds": 12,
        "weapons": [
            {
                "attacks": 4,
                "dmg_crit": 3,
                "dmg_hit": 1,
                "max_range": 1,
                "min_range": 0,
                "runemark": "club",
                "strength": 3
            }
        ],
        "runemarks": [
            "hero",
            "minion"
        ],
        "points": 100
    },
    {
        "_id": "a08a58ef",
        "name": "Skink Alpha with Boltspitter and Moonstone Club",
        "warband": "Seraphon",
        "subfaction": "",
        "grand_alliance": "order",
        "movement": 6,
        "toughness": 2,
        "wounds": 12,
        "weapons": [
            {
                "attacks": 4,
                "dmg_crit": 3,
                "dmg_hit": 1,
                "max_range": 1,
                "min_range": 0,
                "runemark": "club",
                "strength": 3
            },
            {
                "attacks": 2,
                "dmg_crit": 2,
                "dmg_hit": 1,
                "max_range": 8,
                "min_range": 0,
                "runemark": "ranged",
                "strength": 1
            }
        ],
        "runemarks": [
            "hero",
            "minion"
        ],
        "points": 105
    },
    {
        "_id": "fde45ce6",
        "name": "Saurus Guard",
        "warband": "Seraphon",
        "subfaction": "",
        "grand_alliance": "order",
        "movement": 4,
        "toughness": 5,
        "wounds": 15,
        "weapons": [
            {
                "attacks": 3,
                "dmg_crit": 4,
                "dmg_hit": 2,
                "max_range": 2,
                "min_range": 0,
                "runemark": "club",
                "strength": 4
            }
        ],
        "runemarks": [
            "warrior"
        ],
        "points": 120
    },
    {
        "_id": "27112a0a",
        "name": "Skink Priest",
        "warband": "Seraphon",
        "subfaction": "",
        "grand_alliance": "order",
        "movement": 6,
        "toughness": 3,
        "wounds": 18,
        "weapons": [
            {
                "attacks": 3,
                "dmg_crit": 3,
                "dmg_hit": 1,
                "max_range": 2,
                "min_range": 0,
                "runemark": "club",
                "strength": 3
            },
            {
                "attacks": 2,
                "dmg_crit": 5,
                "dmg_hit": 2,
                "max_range": 7,
                "min_range": 3,
                "runemark": "blast",
                "strength": 3
            }
        ],
        "runemarks": [
            "hero",
            "minion",
            "priest"
        ],
        "points": 130
    },
    {
        "_id": "f147c1ba",
        "name": "Salamander",
        "warband": "Seraphon",
        "subfaction": "",
        "grand_alliance": "order",
        "movement": 6,
        "toughness": 3,
        "wounds": 16,
        "weapons": [
            {
                "attacks": 2,
                "dmg_crit": 6,
                "dmg_hit": 3,
                "max_range": 7,
                "min_range": 0,
                "runemark": "blast",
                "strength": 4
            }
        ],
        "runemarks": [
            "beast"
        ],
        "points": 135
    },
    {
        "_id": "eeab8259",
        "name": "Saurus Warrior Alpha",
        "warband": "Seraphon",
        "subfaction": "",
        "grand_alliance": "order",
        "movement": 4,
        "toughness": 4,
        "wounds": 16,
        "weapons": [
            {
                "attacks": 4,
                "dmg_crit": 4,
                "dmg_hit": 2,
                "max_range": 1,
                "min_range": 0,
                "runemark": "club",
                "strength": 4
            }
        ],
        "runemarks": [
            "hero",
            "warrior"
        ],
        "points": 135
    },
    {
        "_id": "63234b3a",
        "name": "Razordon",
        "warband": "Seraphon",
        "subfaction": "",
        "grand_alliance": "order",
        "movement": 6,
        "toughness": 4,
        "wounds": 16,
        "weapons": [
            {
                "attacks": 5,
                "dmg_crit": 3,
                "dmg_hit": 1,
                "max_range": 12,
                "min_range": 0,
                "runemark": "blast",
                "strength": 3
            }
        ],
        "runemarks": [
            "beast"
        ],
        "points": 145
    },
    {
        "_id": "a4d524f1",
        "name": "Aggradon Lancer Alpha with Celestite Club",
        "warband": "Seraphon",
        "subfaction": "",
        "grand_alliance": "order",
        "movement": 8,
        "toughness": 4,
        "wounds": 25,
        "weapons": [
            {
                "attacks": 4,
                "dmg_crit": 4,
                "dmg_hit": 3,
                "max_range": 1,
                "min_range": 0,
                "runemark": "club",
                "strength": 4
            }
        ],
        "runemarks": [
            "hero",
            "warrior",
            "mount"
        ],
        "points": 245
    },
    {
        "_id": "85f572ca",
        "name": "Aggradon Lancer Alpha with Celestite Spear",
        "warband": "Seraphon",
        "subfaction": "",
        "grand_alliance": "order",
        "movement": 8,
        "toughness": 4,
        "wounds": 25,
        "weapons": [
            {
                "attacks": 4,
                "dmg_crit": 5,
                "dmg_hit": 2,
                "max_range": 2,
                "min_range": 0,
                "runemark": "spear",
                "strength": 4
            }
        ],
        "runemarks": [
            "hero",
            "warrior",
            "mount"
        ],
        "points": 235
    },
    {
        "_id": "eb7ea713",
        "name": "Raptadon Hunter Alpha",
        "warband": "Seraphon",
        "subfaction": "",
        "grand_alliance": "order",
        "movement": 10,
        "toughness": 2,
        "wounds": 14,
        "weapons": [
            {
                "attacks": 3,
                "dmg_crit": 3,
                "dmg_hit": 1,
                "max_range": 2,
                "min_range": 0,
                "runemark": "spear",
                "strength": 2
            },
            {
                "attacks": 2,
                "dmg_crit": 3,
                "dmg_hit": 1,
                "max_range": 8,
                "min_range": 3,
                "runemark": "ranged",
                "strength": 3
            }
        ],
        "runemarks": [
            "hero",
            "minion",
            "mount"
        ],
        "points": 140
    },
    {
        "_id": "d52aba81",
        "name": "Raptadon Charger Alpha",
        "warband": "Seraphon",
        "subfaction": "",
        "grand_alliance": "order",
        "movement": 10,
        "toughness": 2,
        "wounds": 14,
        "weapons": [
            {
                "attacks": 4,
                "dmg_crit": 3,
                "dmg_hit": 1,
                "max_range": 1,
                "min_range": 0,
                "runemark": "mace",
                "strength": 3
            }
        ],
        "runemarks": [
            "hero",
            "minion",
            "mount"
        ],
        "points": 135
    },
    {
        "_id": "ebfc0cf2",
        "name": "Saurus Scar-Veteran on Aggradon",
        "warband": "Seraphon",
        "subfaction": "",
        "grand_alliance": "order",
        "movement": 8,
        "toughness": 4,
        "wounds": 30,
        "weapons": [
            {
                "attacks": 4,
                "dmg_crit": 5,
                "dmg_hit": 3,
                "max_range": 1,
                "min_range": 0,
                "runemark": "spear",
                "strength": 5
            }
        ],
        "runemarks": [
            "hero",
            "warrior",
            "mount"
        ],
        "points": 295
    },
    {
        "_id": "26043eca",
        "name": "Aggradon Lancer with Celestite Club",
        "warband": "Seraphon",
        "subfaction": "",
        "grand_alliance": "order",
        "movement": 8,
        "toughness": 4,
        "wounds": 20,
        "weapons": [
            {
                "attacks": 3,
                "dmg_crit": 4,
                "dmg_hit": 3,
                "max_range": 1,
                "min_range": 0,
                "runemark": "club",
                "strength": 4
            }
        ],
        "runemarks": [
            "warrior",
            "mount"
        ],
        "points": 185
    },
    {
        "_id": "9f1e68b5",
        "name": "Aggradon Lancer with Celestite Spear",
        "warband": "Seraphon",
        "subfaction": "",
        "grand_alliance": "order",
        "movement": 8,
        "toughness": 4,
        "wounds": 20,
        "weapons": [
            {
                "attacks": 3,
                "dmg_crit": 5,
                "dmg_hit": 2,
                "max_range": 2,
                "min_range": 0,
                "runemark": "spear",
                "strength": 4
            }
        ],
        "runemarks": [
            "warrior",
            "mount"
        ],
        "points": 180
    },
    {
        "_id": "1545eb4d",
        "name": "Raptadon Charger",
        "warband": "Seraphon",
        "subfaction": "",
        "grand_alliance": "order",
        "movement": 10,
        "toughness": 2,
        "wounds": 12,
        "weapons": [
            {
                "attacks": 3,
                "dmg_crit": 3,
                "dmg_hit": 1,
                "max_range": 1,
                "min_range": 0,
                "runemark": "mace",
                "strength": 3
            }
        ],
        "runemarks": [
            "minion",
            "mount"
        ],
        "points": 110
    },
    {
        "_id": "5b66f32a",
        "name": "Raptadon Hunter",
        "warband": "Seraphon",
        "subfaction": "",
        "grand_alliance": "order",
        "movement": 10,
        "toughness": 2,
        "wounds": 12,
        "weapons": [
            {
                "attacks": 3,
                "dmg_crit": 3,
                "dmg_hit": 1,
                "max_range": 2,
                "min_range": 0,
                "runemark": "spear",
                "strength": 2
            },
            {
                "attacks": 2,
                "dmg_crit": 3,
                "dmg_hit": 1,
                "max_range": 8,
                "min_range": 3,
                "runemark": "ranged",
                "strength": 3
            }
        ],
        "runemarks": [
            "minion",
            "mount"
        ],
        "points": 120
    },
    {
        "_id": "ddbd41e4",
        "name": "Spawn of Chotec",
        "warband": "Seraphon",
        "subfaction": "",
        "grand_alliance": "order",
        "movement": 6,
        "toughness": 4,
        "wounds": 18,
        "weapons": [
            {
                "attacks": 2,
                "dmg_crit": 4,
                "dmg_hit": 2,
                "max_range": 1,
                "min_range": 0,
                "runemark": "fangs",
                "strength": 4
            },
            {
                "attacks": 2,
                "dmg_crit": 3,
                "dmg_hit": 2,
                "max_range": 7,
                "min_range": 3,
                "runemark": "blast",
                "strength": 5
            }
        ],
        "runemarks": [
            "beast"
        ],
        "points": 130
    },
    {
        "_id": "9bc16a41",
        "name": "Kroxigor",
        "warband": "Seraphon",
        "subfaction": "",
        "grand_alliance": "order",
        "movement": 4,
        "toughness": 5,
        "wounds": 28,
        "weapons": [
            {
                "attacks": 2,
                "dmg_crit": 8,
                "dmg_hit": 4,
                "max_range": 2,
                "min_range": 0,
                "runemark": "mace",
                "strength": 6
            }
        ],
        "runemarks": [
            "warrior",
            "brute"
        ],
        "points": 200
    },
    {
        "_id": "c95ad268",
        "name": "Kroxigor Warspawned",
        "warband": "Seraphon",
        "subfaction": "",
        "grand_alliance": "order",
        "movement": 4,
        "toughness": 5,
        "wounds": 28,
        "weapons": [
            {
                "attacks": 3,
                "dmg_crit": 6,
                "dmg_hit": 3,
                "max_range": 2,
                "min_range": 0,
                "runemark": "mace",
                "strength": 5
            }
        ],
        "runemarks": [
            "warrior",
            "sentience"
        ],
        "points": 205
    },
    {
        "_id": "97071a01",
        "name": "Skink Starpriest",
        "warband": "Seraphon",
        "subfaction": "",
        "grand_alliance": "order",
        "movement": 6,
        "toughness": 3,
        "wounds": 18,
        "weapons": [
            {
                "attacks": 3,
                "dmg_crit": 4,
                "dmg_hit": 1,
                "max_range": 2,
                "min_range": 0,
                "runemark": "club",
                "strength": 3
            },
            {
                "attacks": 2,
                "dmg_crit": 6,
                "dmg_hit": 3,
                "max_range": 7,
                "min_range": 3,
                "runemark": "blast",
                "strength": 3
            }
        ],
        "runemarks": [
            "hero",
            "minion",
            "priest"
        ],
        "points": 145
    },
    {
        "_id": "6c790e4b",
        "name": "Saurus Astrolith Bearer",
        "warband": "Seraphon",
        "subfaction": "",
        "grand_alliance": "order",
        "movement": 4,
        "toughness": 4,
        "wounds": 25,
        "weapons": [
            {
                "attacks": 3,
                "dmg_crit": 4,
                "dmg_hit": 2,
                "max_range": 1,
                "min_range": 0,
                "runemark": "axe",
                "strength": 4
            }
        ],
        "runemarks": [
            "hero",
            "warrior",
            "icon-bearer"
        ],
        "points": 155
    },
    {
        "_id": "63066e2a",
        "name": "Saurus Knight with Celestite Blade",
        "warband": "Seraphon",
        "subfaction": "",
        "grand_alliance": "order",
        "movement": 6,
        "toughness": 4,
        "wounds": 20,
        "weapons": [
            {
                "attacks": 4,
                "dmg_crit": 3,
                "dmg_hit": 2,
                "max_range": 1,
                "min_range": 0,
                "runemark": "club",
                "strength": 4
            }
        ],
        "runemarks": [
            "warrior",
            "mount"
        ],
        "points": 160
    },
    {
        "_id": "6da35a11",
        "name": "Saurus Knight with Celestite Warspear",
        "warband": "Seraphon",
        "subfaction": "",
        "grand_alliance": "order",
        "movement": 6,
        "toughness": 4,
        "wounds": 20,
        "weapons": [
            {
                "attacks": 4,
                "dmg_crit": 4,
                "dmg_hit": 2,
                "max_range": 2,
                "min_range": 0,
                "runemark": "spear",
                "strength": 4
            }
        ],
        "runemarks": [
            "warrior",
            "mount"
        ],
        "points": 165
    },
    {
        "_id": "a17f32e9",
        "name": "Ripperdactyl Rider",
        "warband": "Seraphon",
        "subfaction": "",
        "grand_alliance": "order",
        "movement": 10,
        "toughness": 4,
        "wounds": 15,
        "weapons": [
            {
                "attacks": 3,
                "dmg_crit": 4,
                "dmg_hit": 2,
                "max_range": 1,
                "min_range": 0,
                "runemark": "fangs",
                "strength": 4
            }
        ],
        "runemarks": [
            "fly",
            "destroyer"
        ],
        "points": 170
    },
    {
        "_id": "73828e4c",
        "name": "Terradon Rider with Sunleech Bolas",
        "warband": "Seraphon",
        "subfaction": "",
        "grand_alliance": "order",
        "movement": 12,
        "toughness": 3,
        "wounds": 15,
        "weapons": [
            {
                "attacks": 3,
                "dmg_crit": 4,
                "dmg_hit": 2,
                "max_range": 1,
                "min_range": 0,
                "runemark": "fangs",
                "strength": 4
            },
            {
                "attacks": 3,
                "dmg_crit": 4,
                "dmg_hit": 1,
                "max_range": 3,
                "min_range": 0,
                "runemark": "reach",
                "strength": 2
            }
        ],
        "runemarks": [
            "fly",
            "frenzied"
        ],
        "points": 170
    },
    {
        "_id": "ad0c18b7",
        "name": "Terradon Rider with Starstrike Javelin",
        "warband": "Seraphon",
        "subfaction": "",
        "grand_alliance": "order",
        "movement": 12,
        "toughness": 3,
        "wounds": 15,
        "weapons": [
            {
                "attacks": 3,
                "dmg_crit": 4,
                "dmg_hit": 2,
                "max_range": 1,
                "min_range": 0,
                "runemark": "fangs",
                "strength": 4
            },
            {
                "attacks": 1,
                "dmg_crit": 4,
                "dmg_hit": 1,
                "max_range": 8,
                "min_range": 0,
                "runemark": "spear",
                "strength": 3
            }
        ],
        "runemarks": [
            "fly",
            "frenzied"
        ],
        "points": 170
    },
    {
        "_id": "0786e4e6",
        "name": "Saurus Guard Alpha",
        "warband": "Seraphon",
        "subfaction": "",
        "grand_alliance": "order",
        "movement": 4,
        "toughness": 5,
        "wounds": 20,
        "weapons": [
            {
                "attacks": 4,
                "dmg_crit": 5,
                "dmg_hit": 2,
                "max_range": 2,
                "min_range": 0,
                "runemark": "club",
                "strength": 4
            }
        ],
        "runemarks": [
            "hero",
            "warrior"
        ],
        "points": 175
    },
    {
        "_id": "cfdb15bd",
        "name": "Saurus Oldblood",
        "warband": "Seraphon",
        "subfaction": "",
        "grand_alliance": "order",
        "movement": 4,
        "toughness": 5,
        "wounds": 25,
        "weapons": [
            {
                "attacks": 4,
                "dmg_crit": 4,
                "dmg_hit": 2,
                "max_range": 1,
                "min_range": 0,
                "runemark": "club",
                "strength": 4
            }
        ],
        "runemarks": [
            "hero",
            "warrior"
        ],
        "points": 175
    },
    {
        "_id": "60ee60c9",
        "name": "Saurus Sunblood",
        "warband": "Seraphon",
        "subfaction": "",
        "grand_alliance": "order",
        "movement": 4,
        "toughness": 5,
        "wounds": 25,
        "weapons": [
            {
                "attacks": 4,
                "dmg_crit": 5,
                "dmg_hit": 2,
                "max_range": 1,
                "min_range": 0,
                "runemark": "club",
                "strength": 4
            }
        ],
        "runemarks": [
            "hero",
            "warrior"
        ],
        "points": 180
    },
    {
        "_id": "d25dc24f",
        "name": "Skink Starseer",
        "warband": "Seraphon",
        "subfaction": "",
        "grand_alliance": "order",
        "movement": 4,
        "toughness": 3,
        "wounds": 20,
        "weapons": [
            {
                "attacks": 2,
                "dmg_crit": 6,
                "dmg_hit": 3,
                "max_range": 12,
                "min_range": 0,
                "runemark": "blast",
                "strength": 4
            }
        ],
        "runemarks": [
            "fly",
            "hero",
            "priest"
        ],
        "points": 180
    },
    {
        "_id": "ba3c9ea2",
        "name": "Saurus Eternity Warden",
        "warband": "Seraphon",
        "subfaction": "",
        "grand_alliance": "order",
        "movement": 4,
        "toughness": 4,
        "wounds": 28,
        "weapons": [
            {
                "attacks": 3,
                "dmg_crit": 6,
                "dmg_hit": 3,
                "max_range": 1,
                "min_range": 0,
                "runemark": "mace",
                "strength": 5
            }
        ],
        "runemarks": [
            "hero",
            "warrior"
        ],
        "points": 190
    },
    {
        "_id": "32683094",
        "name": "Saurus Knight Alpha",
        "warband": "Seraphon",
        "subfaction": "",
        "grand_alliance": "order",
        "movement": 6,
        "toughness": 4,
        "wounds": 25,
        "weapons": [
            {
                "attacks": 4,
                "dmg_crit": 5,
                "dmg_hit": 2,
                "max_range": 1,
                "min_range": 0,
                "runemark": "club",
                "strength": 4
            }
        ],
        "runemarks": [
            "hero",
            "warrior",
            "mount"
        ],
        "points": 195
    },
    {
        "_id": "eacd821f",
        "name": "Terradon Rider Alpha with Starstrike Javelin",
        "warband": "Seraphon",
        "subfaction": "",
        "grand_alliance": "order",
        "movement": 12,
        "toughness": 3,
        "wounds": 20,
        "weapons": [
            {
                "attacks": 3,
                "dmg_crit": 4,
                "dmg_hit": 2,
                "max_range": 1,
                "min_range": 0,
                "runemark": "spear",
                "strength": 4
            },
            {
                "attacks": 2,
                "dmg_crit": 4,
                "dmg_hit": 1,
                "max_range": 8,
                "min_range": 0,
                "runemark": "ranged",
                "strength": 3
            }
        ],
        "runemarks": [
            "fly",
            "hero",
            "frenzied"
        ],
        "points": 195
    },
    {
        "_id": "ab0f3a47",
        "name": "Terradon Rider Alpha with Sunleech Bolas",
        "warband": "Seraphon",
        "subfaction": "",
        "grand_alliance": "order",
        "movement": 12,
        "toughness": 3,
        "wounds": 20,
        "weapons": [
            {
                "attacks": 3,
                "dmg_crit": 4,
                "dmg_hit": 2,
                "max_range": 1,
                "min_range": 0,
                "runemark": "reach",
                "strength": 4
            },
            {
                "attacks": 4,
                "dmg_crit": 4,
                "dmg_hit": 1,
                "max_range": 3,
                "min_range": 0,
                "runemark": "ranged",
                "strength": 3
            }
        ],
        "runemarks": [
            "fly",
            "hero",
            "frenzied"
        ],
        "points": 200
    },
    {
        "_id": "8c2e4bbc",
        "name": "Saurus Scar-Veteran on Cold One",
        "warband": "Seraphon",
        "subfaction": "",
        "grand_alliance": "order",
        "movement": 7,
        "toughness": 5,
        "wounds": 28,
        "weapons": [
            {
                "attacks": 4,
                "dmg_crit": 4,
                "dmg_hit": 2,
                "max_range": 1,
                "min_range": 0,
                "runemark": "axe",
                "strength": 4
            }
        ],
        "runemarks": [
            "hero",
            "warrior",
            "mount"
        ],
        "points": 215
    },
    {
        "_id": "bc5abb52",
        "name": "Ripperdactyl Rider Alpha",
        "warband": "Seraphon",
        "subfaction": "",
        "grand_alliance": "order",
        "movement": 10,
        "toughness": 4,
        "wounds": 20,
        "weapons": [
            {
                "attacks": 4,
                "dmg_crit": 4,
                "dmg_hit": 2,
                "max_range": 1,
                "min_range": 0,
                "runemark": "fangs",
                "strength": 4
            }
        ],
        "runemarks": [
            "hero",
            "fly",
            "destroyer"
        ],
        "points": 220
    },
    {
        "_id": "e86b81b0",
        "name": "Terradon Chief",
        "warband": "Seraphon",
        "subfaction": "",
        "grand_alliance": "order",
        "movement": 12,
        "toughness": 3,
        "wounds": 25,
        "weapons": [
            {
                "attacks": 4,
                "dmg_crit": 4,
                "dmg_hit": 2,
                "max_range": 1,
                "min_range": 0,
                "runemark": "sword",
                "strength": 4
            }
        ],
        "runemarks": [
            "fly",
            "hero",
            "agile"
        ],
        "points": 230
    },
    {
        "_id": "6bd9512b",
        "name": "Ripperdactyl Chief",
        "warband": "Seraphon",
        "subfaction": "",
        "grand_alliance": "order",
        "movement": 10,
        "toughness": 4,
        "wounds": 25,
        "weapons": [
            {
                "attacks": 4,
                "dmg_crit": 4,
                "dmg_hit": 2,
                "max_range": 1,
                "min_range": 0,
                "runemark": "axe",
                "strength": 4
            }
        ],
        "runemarks": [
            "fly",
            "hero",
            "destroyer"
        ],
        "points": 235
    },
    {
        "_id": "74f71987",
        "name": "Slann Starmaster",
        "warband": "Seraphon",
        "subfaction": "",
        "grand_alliance": "order",
        "movement": 4,
        "toughness": 4,
        "wounds": 32,
        "weapons": [
            {
                "attacks": 3,
                "dmg_crit": 6,
                "dmg_hit": 3,
                "max_range": 12,
                "min_range": 0,
                "runemark": "blast",
                "strength": 4
            }
        ],
        "runemarks": [
            "fly",
            "hero",
            "mystic"
        ],
        "points": 265
    },
    {
        "_id": "add3b00a",
        "name": "Xepic",
        "warband": "Seraphon",
        "subfaction": "The Starblood Stalkers",
        "grand_alliance": "order",
        "movement": 6,
        "toughness": 3,
        "wounds": 10,
        "weapons": [
            {
                "attacks": 3,
                "dmg_crit": 3,
                "dmg_hit": 1,
                "max_range": 1,
                "min_range": 0,
                "runemark": "club",
                "strength": 3
            }
        ],
        "runemarks": [
            "minion"
        ],
        "points": 75
    },
    {
        "_id": "b8021dae",
        "name": "Otapatl",
        "warband": "Seraphon",
        "subfaction": "The Starblood Stalkers",
        "grand_alliance": "order",
        "movement": 6,
        "toughness": 2,
        "wounds": 10,
        "weapons": [
            {
                "attacks": 2,
                "dmg_crit": 2,
                "dmg_hit": 1,
                "max_range": 1,
                "min_range": 0,
                "runemark": "unarmed",
                "strength": 3
            },
            {
                "attacks": 2,
                "dmg_crit": 5,
                "dmg_hit": 1,
                "max_range": 12,
                "min_range": 0,
                "runemark": "ranged",
                "strength": 3
            }
        ],
        "runemarks": [
            "minion",
            "scout"
        ],
        "points": 80
    },
    {
        "_id": "a0be7ffd",
        "name": "Tok",
        "warband": "Seraphon",
        "subfaction": "The Starblood Stalkers",
        "grand_alliance": "order",
        "movement": 6,
        "toughness": 2,
        "wounds": 10,
        "weapons": [
            {
                "attacks": 3,
                "dmg_crit": 3,
                "dmg_hit": 1,
                "max_range": 1,
                "min_range": 0,
                "runemark": "club",
                "strength": 3
            },
            {
                "attacks": 2,
                "dmg_crit": 4,
                "dmg_hit": 1,
                "max_range": 12,
                "min_range": 0,
                "runemark": "ranged",
                "strength": 3
            }
        ],
        "runemarks": [
            "minion"
        ],
        "points": 80
    },
    {
        "_id": "d7ee917f",
        "name": "Huachi",
        "warband": "Seraphon",
        "subfaction": "The Starblood Stalkers",
        "grand_alliance": "order",
        "movement": 6,
        "toughness": 3,
        "wounds": 10,
        "weapons": [
            {
                "attacks": 3,
                "dmg_crit": 3,
                "dmg_hit": 1,
                "max_range": 1,
                "min_range": 0,
                "runemark": "dagger",
                "strength": 3
            },
            {
                "attacks": 1,
                "dmg_crit": 4,
                "dmg_hit": 1,
                "max_range": 8,
                "min_range": 0,
                "runemark": "spear",
                "strength": 3
            }
        ],
        "runemarks": [
            "minion"
        ],
        "points": 95
    },
    {
        "_id": "76ecea40",
        "name": "Kixi-Taka, The Diviner",
        "warband": "Seraphon",
        "subfaction": "The Starblood Stalkers",
        "grand_alliance": "order",
        "movement": 6,
        "toughness": 3,
        "wounds": 18,
        "weapons": [
            {
                "attacks": 3,
                "dmg_crit": 4,
                "dmg_hit": 1,
                "max_range": 2,
                "min_range": 0,
                "runemark": "club",
                "strength": 3
            },
            {
                "attacks": 2,
                "dmg_crit": 6,
                "dmg_hit": 3,
                "max_range": 7,
                "min_range": 3,
                "runemark": "blast",
                "strength": 3
            }
        ],
        "runemarks": [
            "hero",
            "minion"
        ],
        "points": 130
    },
    {
        "_id": "1e35ab7c",
        "name": "Klaq-Trok",
        "warband": "Seraphon",
        "subfaction": "The Starblood Stalkers",
        "grand_alliance": "order",
        "movement": 4,
        "toughness": 5,
        "wounds": 28,
        "weapons": [
            {
                "attacks": 4,
                "dmg_crit": 4,
                "dmg_hit": 2,
                "max_range": 1,
                "min_range": 0,
                "runemark": "club",
                "strength": 4
            }
        ],
        "runemarks": [
            "warrior"
        ],
        "points": 175
    },
    {
        "_id": "ffguvt5r",
        "name": "Kro-Jax, the Aegis",
        "warband": "Seraphon",
        "subfaction": "Jaws of Itzl",
        "grand_alliance": "order",
        "movement": 4,
        "toughness": 5,
        "wounds": 30,
        "weapons": [
            {
                "attacks": 4,
                "dmg_crit": 5,
                "dmg_hit": 3,
                "max_range": 1,
                "min_range": 0,
                "runemark": "club",
                "strength": 5
            }
        ],
        "runemarks": [
            "hero",
            "warrior"
        ],
        "points": 240
    },
    {
        "_id": "bolny32m",
        "name": "So-Kar",
        "warband": "Seraphon",
        "subfaction": "Jaws of Itzl",
        "grand_alliance": "order",
        "movement": 4,
        "toughness": 4,
        "wounds": 16,
        "weapons": [
            {
                "attacks": 4,
                "dmg_crit": 4,
                "dmg_hit": 2,
                "max_range": 1,
                "min_range": 0,
                "runemark": "sword",
                "strength": 4
            }
        ],
        "runemarks": [
            "bulwark",
            "warrior"
        ],
        "points": 140
    },
    {
        "_id": "bolny32m",
        "name": "Ro-Tak , the Guardian",
        "warband": "Seraphon",
        "subfaction": "Jaws of Itzl",
        "grand_alliance": "order",
        "movement": 4,
        "toughness": 4,
        "wounds": 16,
        "weapons": [
            {
                "attacks": 4,
                "dmg_crit": 4,
                "dmg_hit": 2,
                "max_range": 2,
                "min_range": 0,
                "runemark": "spear",
                "strength": 4
            }
        ],
        "runemarks": [
            "bulwark",
            "warrior"
        ],
        "points": 150
    }
]
